
[
  {
    "title": "Úvod",
    "chapter_number": "",
    "page_number": "3",
    "children": []
  },
  {
    "title": "Úpadek českého Inářství. Dopis p. Mastného †",
    "chapter_number": "",
    "page_number": "5",
    "children": []
  },
  {
    "title": "Jakou hodnotu má do sebe český len?",
    "chapter_number": "",
    "page_number": "10",
    "children": []
  },
  {
    "title": "Může a má se len v Čechách pěstovati?",
    "chapter_number": "",
    "page_number": "13",
    "children": []
  },
  {
    "title": "Mohou-li kdy čeští hospodáři s pěstováním Inu spokojeni býti?",
    "chapter_number": "",
    "page_number": "16",
    "children": []
  },
  {
    "title": "Jak se má len pěstovati a upravovati?",
    "chapter_number": "",
    "page_number": "18",
    "children": []
  },
  {
    "title": "Pěstování Inu v Belgii",
    "chapter_number": "",
    "page_number": "19",
    "children": []
  },
  {
    "title": "Vyňatky z mého referátu o pěstování a zdělávání Inu v cizině",
    "chapter_number": "",
    "page_number": "20",
    "children": []
  },
  {
    "title": "Pozorování",
    "chapter_number": "",
    "page_number": "20",
    "children": []
  },
  {
    "title": "Úvahy: Podmínky zdaru Inu.",
    "chapter_number": "",
    "page_number": "25",
    "children": []
  },
  {
    "title": "Ponebí",
    "chapter_number": "",
    "page_number": "25",
    "children": []
  },
  {
    "title": "Půda",
    "chapter_number": "",
    "page_number": "25",
    "children": []
  },
  {
    "title": "Semeno",
    "chapter_number": "",
    "page_number": "26",
    "children": []
  },
  {
    "title": "Postup v osevu",
    "chapter_number": "",
    "page_number": "27",
    "children": []
  },
  {
    "title": "Úprava půdy",
    "chapter_number": "",
    "page_number": "28",
    "children": []
  },
  {
    "title": "Setba",
    "chapter_number": "",
    "page_number": "28",
    "children": []
  },
  {
    "title": "Obdělávání",
    "chapter_number": "",
    "page_number": "29",
    "children": []
  },
  {
    "title": "Sklizba",
    "chapter_number": "",
    "page_number": "30",
    "children": []
  },
  {
    "title": "Připravování močení, zapařování, rosení, lámání a česání lu",
    "chapter_number": "",
    "page_number": "30",
    "children": []
  },
  {
    "title": "Odkud a jak si můžeme Iněné semeno (Iníně) zjednati?",
    "chapter_number": "",
    "page_number": "37",
    "children": []
  },
  {
    "title": "Co se u nás už stalo, aby se lnářství domácí povzneslo?",
    "chapter_number": "",
    "page_number": "39",
    "children": []
  },
  {
    "title": "Prostředky, jimiž lze by bylo Inářství v Čechách povznésti",
    "chapter_number": "",
    "page_number": "42",
    "children": []
  },
  {
    "title": "Dodatek: Berlinská společnost k povznešení Inářství v Německu.",
    "chapter_number": "",
    "page_number": "47",
    "children": []
  },
  {
    "title": "Obchod se Inem a Iněným semenem v Rigavě",
    "chapter_number": "",
    "page_number": "49",
    "children": []
  }
]
