
[
  {
    "title": "Úvod",
    "chapter_number": "",
    "page_number": "1",
    "children": []
  },
  {
    "title": "Morfologie",
    "chapter_number": "",
    "page_number": "3",
    "children": []
  },
  {
    "title": "Kořeny",
    "chapter_number": "",
    "page_number": "4",
    "children": []
  },
  {
    "title": "Pně",
    "chapter_number": "",
    "page_number": "5",
    "children": []
  },
  {
    "title": "Listy",
    "chapter_number": "",
    "page_number": "8",
    "children": []
  },
  {
    "title": "Vedlejší ústroje",
    "chapter_number": "",
    "page_number": "11",
    "children": []
  },
  {
    "title": "Pupeny",
    "chapter_number": "",
    "page_number": "12",
    "children": []
  },
  {
    "title": "Chloupky",
    "chapter_number": "",
    "page_number": "13",
    "children": []
  },
  {
    "title": "Květy",
    "chapter_number": "",
    "page_number": "13",
    "children": []
  },
  {
    "title": "Plody",
    "chapter_number": "",
    "page_number": "20",
    "children": []
  },
  {
    "title": "Semena",
    "chapter_number": "",
    "page_number": "21",
    "children": []
  },
  {
    "title": "Rozdělení rostlin",
    "chapter_number": "",
    "page_number": "21",
    "children": []
  },
  {
    "title": "Rostliny jevnosnubné, krytosemenné",
    "chapter_number": "",
    "page_number": "22",
    "children": [
      {
        "title": "A. Dvojděložné",
        "chapter_number": "",
        "page_number": "22",
        "children": [
          {
            "title": "1. Pryskyřníkovité",
            "chapter_number": "",
            "page_number": "22",
            "children": []
          },
          {
            "title": "2. Dřišťálovité",
            "chapter_number": "",
            "page_number": "27",
            "children": []
          },
          {
            "title": "3. Leknínovité",
            "chapter_number": "",
            "page_number": "28",
            "children": []
          },
          {
            "title": "4. Makovité",
            "chapter_number": "",
            "page_number": "29",
            "children": []
          },
          {
            "title": "5. Dýmnikovité",
            "chapter_number": "",
            "page_number": "30",
            "children": []
          },
          {
            "title": "6. Křížaté",
            "chapter_number": "",
            "page_number": "31",
            "children": []
          },
          {
            "title": "7. Cistovité",
            "chapter_number": "",
            "page_number": "36",
            "children": []
          },
          {
            "title": "8. Rýtovité",
            "chapter_number": "",
            "page_number": "37",
            "children": []
          },
          {
            "title": "9. Violkovité",
            "chapter_number": "",
            "page_number": "37",
            "children": []
          },
          {
            "title": "10. Rosničkovité",
            "chapter_number": "",
            "page_number": "38",
            "children": []
          },
          {
            "title": "11. Vitodovité",
            "chapter_number": "",
            "page_number": "39",
            "children": []
          },
          {
            "title": "12. Hvozdíkovité",
            "chapter_number": "",
            "page_number": "39",
            "children": []
          },
          {
            "title": "13. Lnovité",
            "chapter_number": "",
            "page_number": "42",
            "children": []
          },
          {
            "title": "14. Lipovité",
            "chapter_number": "",
            "page_number": "43",
            "children": []
          },
          {
            "title": "15. Čajovníkovité",
            "chapter_number": "",
            "page_number": "43",
            "children": []
          },
          {
            "title": "16. Slezovité",
            "chapter_number": "",
            "page_number": "45",
            "children": []
          },
          {
            "title": "17. Citroníkovité",
            "chapter_number": "",
            "page_number": "46",
            "children": []
          },
          {
            "title": "18. Kakostovité",
            "chapter_number": "",
            "page_number": "46",
            "children": []
          },
          {
            "title": "19. Třezalkovité",
            "chapter_number": "",
            "page_number": "48",
            "children": []
          },
          {
            "title": "20. Javorovité",
            "chapter_number": "",
            "page_number": "48",
            "children": []
          },
          {
            "title": "21. Jirovcovité",
            "chapter_number": "",
            "page_number": "49",
            "children": []
          },
          {
            "title": "22. Révovité",
            "chapter_number": "",
            "page_number": "50",
            "children": []
          },
          {
            "title": "23. Netýkavkovité",
            "chapter_number": "",
            "page_number": "50",
            "children": []
          },
          {
            "title": "24. Stavelovité",
            "chapter_number": "",
            "page_number": "51",
            "children": []
          },
          {
            "title": "25. Routovité",
            "chapter_number": "",
            "page_number": "51",
            "children": []
          },
          {
            "title": "26. Brslenovité",
            "chapter_number": "",
            "page_number": "51",
            "children": []
          },
          {
            "title": "27. Cesminovité",
            "chapter_number": "",
            "page_number": "52",
            "children": []
          },
          {
            "title": "28. Rešetlákovité",
            "chapter_number": "",
            "page_number": "52",
            "children": []
          },
          {
            "title": "29. Motýlokvětné",
            "chapter_number": "",
            "page_number": "53",
            "children": []
          },
          {
            "title": "30. Mandloňovité",
            "chapter_number": "",
            "page_number": "59",
            "children": []
          },
          {
            "title": "31. Jabloňovité",
            "chapter_number": "",
            "page_number": "61",
            "children": []
          },
          {
            "title": "32. Růžovité",
            "chapter_number": "",
            "page_number": "63",
            "children": []
          },
          {
            "title": "33. Pupalkovité",
            "chapter_number": "",
            "page_number": "67",
            "children": []
          },
          {
            "title": "34. Kyprejovité",
            "chapter_number": "",
            "page_number": "68",
            "children": []
          },
          {
            "title": "35. Tykvicovité",
            "chapter_number": "",
            "page_number": "68",
            "children": []
          },
          {
            "title": "36. Tučnicovité",
            "chapter_number": "",
            "page_number": "69",
            "children": []
          },
          {
            "title": "37. Meruzalkovité",
            "chapter_number": "",
            "page_number": "71",
            "children": []
          },
          {
            "title": "38. Lomikamenovité",
            "chapter_number": "",
            "page_number": "71",
            "children": []
          },
          {
            "title": "39. Okoličnaté",
            "chapter_number": "",
            "page_number": "73",
            "children": []
          },
          {
            "title": "40. Břečtanovité",
            "chapter_number": "",
            "page_number": "77",
            "children": []
          },
          {
            "title": "41. Jmelovité",
            "chapter_number": "",
            "page_number": "77",
            "children": []
          },
          {
            "title": "42. Dřinovité",
            "chapter_number": "",
            "page_number": "77",
            "children": []
          },
          {
            "title": "43. Zimolezovité",
            "chapter_number": "",
            "page_number": "78",
            "children": []
          },
          {
            "title": "44. Mořenovité",
            "chapter_number": "",
            "page_number": "79",
            "children": []
          },
          {
            "title": "45. Kozlíkovité",
            "chapter_number": "",
            "page_number": "81",
            "children": []
          },
          {
            "title": "46. Štětkovité",
            "chapter_number": "",
            "page_number": "81",
            "children": []
          },
          {
            "title": "47. Složnokvětné",
            "chapter_number": "",
            "page_number": "82",
            "children": []
          },
          {
            "title": "48. Zvonkovité",
            "chapter_number": "",
            "page_number": "89",
            "children": []
          },
          {
            "title": "49. Vřesovité",
            "chapter_number": "",
            "page_number": "89",
            "children": []
          },
          {
            "title": "50. Prvosenkovité",
            "chapter_number": "",
            "page_number": "92",
            "children": []
          },
          {
            "title": "51. Olivovité",
            "chapter_number": "",
            "page_number": "93",
            "children": []
          },
          {
            "title": "52. Brčálovité",
            "chapter_number": "",
            "page_number": "94",
            "children": []
          },
          {
            "title": "53. Hořcovité",
            "chapter_number": "",
            "page_number": "95",
            "children": []
          },
          {
            "title": "54. Svlačcovité",
            "chapter_number": "",
            "page_number": "96",
            "children": []
          },
          {
            "title": "55. Brutnákovité",
            "chapter_number": "",
            "page_number": "96",
            "children": []
          },
          {
            "title": "56. Lilkovité",
            "chapter_number": "",
            "page_number": "98",
            "children": []
          },
          {
            "title": "57. Krtičníkovité",
            "chapter_number": "",
            "page_number": "100",
            "children": []
          },
          {
            "title": "58. Pyskaté",
            "chapter_number": "",
            "page_number": "103",
            "children": []
          },
          {
            "title": "59. Jitrocélovité",
            "chapter_number": "",
            "page_number": "107",
            "children": []
          },
          {
            "title": "60. Chmerkovité",
            "chapter_number": "",
            "page_number": "108",
            "children": []
          },
          {
            "title": "61. Lebedovité",
            "chapter_number": "",
            "page_number": "108",
            "children": []
          },
          {
            "title": "62. Rdesnovité",
            "chapter_number": "",
            "page_number": "110",
            "children": []
          },
          {
            "title": "63. Lýkovcovité",
            "chapter_number": "",
            "page_number": "111",
            "children": []
          },
          {
            "title": "64. Podražcovité",
            "chapter_number": "",
            "page_number": "111",
            "children": []
          },
          {
            "title": "65. Pryšcovité",
            "chapter_number": "",
            "page_number": "112",
            "children": []
          },
          {
            "title": "66. Kopřivovité",
            "chapter_number": "",
            "page_number": "113",
            "children": []
          },
          {
            "title": "67. Jehnědokvětné",
            "chapter_number": "",
            "page_number": "115",
            "children": []
          },
          {
            "title": "68. Jilmovité",
            "chapter_number": "",
            "page_number": "119",
            "children": []
          }
        ]
      },
      {
        "title": "B. Jednoděložné",
        "chapter_number": "",
        "page_number": "121",
        "children": [
          {
            "title": "1. Aronovité",
            "chapter_number": "",
            "page_number": "121",
            "children": []
          },
          {
            "title": "2. Orobincovité",
            "chapter_number": "",
            "page_number": "122",
            "children": []
          },
          {
            "title": "3. Palmy",
            "chapter_number": "",
            "page_number": "122",
            "children": []
          },
          {
            "title": "4. Okřehky",
            "chapter_number": "",
            "page_number": "124",
            "children": []
          },
          {
            "title": "5. Rečankovité",
            "chapter_number": "",
            "page_number": "124",
            "children": []
          },
          {
            "title": "6. Žabníkovité",
            "chapter_number": "",
            "page_number": "124",
            "children": []
          },
          {
            "title": "7. Vstavačovité",
            "chapter_number": "",
            "page_number": "125",
            "children": []
          },
          {
            "title": "8. Banánovité",
            "chapter_number": "",
            "page_number": "128",
            "children": []
          },
          {
            "title": "9. Kosatcovité",
            "chapter_number": "",
            "page_number": "128",
            "children": []
          },
          {
            "title": "10. Narciskovité",
            "chapter_number": "",
            "page_number": "129",
            "children": []
          },
          {
            "title": "11. Liliovité",
            "chapter_number": "",
            "page_number": "130",
            "children": []
          },
          {
            "title": "12. Ocúnovité",
            "chapter_number": "",
            "page_number": "134",
            "children": []
          },
          {
            "title": "13. Sitinovité",
            "chapter_number": "",
            "page_number": "134",
            "children": []
          },
          {
            "title": "14. Trávy",
            "chapter_number": "",
            "page_number": "134",
            "children": []
          },
          {
            "title": "15. Sáchorovité",
            "chapter_number": "",
            "page_number": "141",
            "children": []
          }
        ]
      }
    ]
  },
  {
    "title": "Rostliny jevnosnubné, nahosemenné",
    "chapter_number": "",
    "page_number": "143",
    "children": [
      {
        "title": "1. Jehličnaté",
        "chapter_number": "",
        "page_number": "143",
        "children": []
      },
      {
        "title": "2. Cykasovité",
        "chapter_number": "",
        "page_number": "146",
        "children": []
      }
    ]
  },
  {
    "title": "Rostliny tajnosnubné",
    "chapter_number": "",
    "page_number": "147",
    "children": [
      {
        "title": "a) Cevnaté",
        "chapter_number": "",
        "page_number": "147",
        "children": [
          {
            "title": "1. Kapradiny",
            "chapter_number": "",
            "page_number": "147",
            "children": []
          },
          {
            "title": "2. Přesličky",
            "chapter_number": "",
            "page_number": "149",
            "children": []
          },
          {
            "title": "3. Plavuně",
            "chapter_number": "",
            "page_number": "150",
            "children": []
          }
        ]
      },
      {
        "title": "b) Mechovité",
        "chapter_number": "",
        "page_number": "151",
        "children": [
          {
            "title": "1. Mechy listnaté",
            "chapter_number": "",
            "page_number": "151",
            "children": []
          },
          {
            "title": "2. Jatrovkovité",
            "chapter_number": "",
            "page_number": "152",
            "children": []
          }
        ]
      },
      {
        "title": "c) Stélkaté",
        "chapter_number": "",
        "page_number": "152",
        "children": [
          {
            "title": "1. Rasy",
            "chapter_number": "",
            "page_number": "152",
            "children": []
          },
          {
            "title": "2. Houby",
            "chapter_number": "",
            "page_number": "154",
            "children": []
          },
          {
            "title": "a) Stopkovýtrusné",
            "chapter_number": "",
            "page_number": "154",
            "children": []
          },
          {
            "title": "β) Vřeckovýtrusné",
            "chapter_number": "",
            "page_number": "158",
            "children": []
          },
          {
            "title": "y) Lyšejníky",
            "chapter_number": "",
            "page_number": "160",
            "children": []
          },
          {
            "title": "d) Vláknité",
            "chapter_number": "",
            "page_number": "161",
            "children": []
          },
          {
            "title": "ε) Poltivé",
            "chapter_number": "",
            "page_number": "162",
            "children": []
          }
        ]
      }
    ]
  }
]
