
[
  {
    "title": "BÁSEŇ „JAROSLAV\"",
    "chapter_number": "",
    "page_number": "",
    "children": []
  },
  {
    "title": "RUKOPISU KRALODVORSKÉHO.",
    "chapter_number": "",
    "page_number": "",
    "children": []
  },
  {
    "title": "(„VOLNÝCH ROZPRAV“ ČÍSLO PRVNÍ).",
    "chapter_number": "",
    "page_number": "",
    "children": []
  },
  {
    "title": "STUDIE HISTORICKO-LITERÁRNÍ.",
    "chapter_number": "",
    "page_number": "",
    "children": []
  },
  {
    "title": "HERMENEGILD JIREČEK.",
    "chapter_number": "",
    "page_number": "",
    "children": []
  }
]
