
[
  {
    "title": "Maga",
    "chapter_number": "",
    "page_number": "94",
    "children": []
  },
  {
    "title": "Hlad",
    "chapter_number": "",
    "page_number": "96",
    "children": []
  },
  {
    "title": "Stařeček",
    "chapter_number": "",
    "page_number": "98",
    "children": []
  },
  {
    "title": "Nevezpivany",
    "chapter_number": "",
    "page_number": "100",
    "children": []
  },
  {
    "title": "Mir",
    "chapter_number": "",
    "page_number": "113",
    "children": []
  },
  {
    "title": "Slovníček a vysvětlení",
    "chapter_number": "",
    "page_number": "115",
    "children": []
  }
]
