
[
  {
    "title": "Úvodem",
    "chapter_number": "",
    "page_number": "3",
    "children": []
  },
  {
    "title": "Z Norska do Karského moře",
    "chapter_number": "",
    "page_number": "7",
    "children": []
  },
  {
    "title": "Návštěva Samojedů",
    "chapter_number": "",
    "page_number": "13",
    "children": []
  },
  {
    "title": "Ledem na sever",
    "chapter_number": "",
    "page_number": "18",
    "children": []
  },
  {
    "title": "Samojedi",
    "chapter_number": "",
    "page_number": "25",
    "children": []
  },
  {
    "title": "Rybolov na Jeniseji",
    "chapter_number": "",
    "page_number": "34",
    "children": []
  },
  {
    "title": "Před další cestou",
    "chapter_number": "",
    "page_number": "37",
    "children": []
  },
  {
    "title": "Po Jeniseji vzhůru",
    "chapter_number": "",
    "page_number": "44",
    "children": []
  },
  {
    "title": "Dudinka a dále na jih",
    "chapter_number": "",
    "page_number": "50",
    "children": []
  },
  {
    "title": "Trojický klášter a dále na jih",
    "chapter_number": "",
    "page_number": "58",
    "children": []
  },
  {
    "title": "Z Verchně-Inbazkoje do Sumarokova",
    "chapter_number": "",
    "page_number": "67",
    "children": []
  },
  {
    "title": "Ze Sumarokova do Jenisejska",
    "chapter_number": "",
    "page_number": "76",
    "children": []
  },
  {
    "title": "Z Jenisejska do Krasnojarska",
    "chapter_number": "",
    "page_number": "84",
    "children": []
  },
  {
    "title": "Kolonisace a vývoj Sibiře",
    "chapter_number": "",
    "page_number": "94",
    "children": []
  },
  {
    "title": "Z Irkutska do Vladivostoku",
    "chapter_number": "",
    "page_number": "99",
    "children": []
  },
  {
    "title": "Ussurské území, Vladivostok a Chabarovsk",
    "chapter_number": "",
    "page_number": "106",
    "children": []
  },
  {
    "title": "Rusko na východě. Žlutá otázka",
    "chapter_number": "",
    "page_number": "111",
    "children": []
  },
  {
    "title": "Amurská oblast a amurská dráha",
    "chapter_number": "",
    "page_number": "118",
    "children": []
  },
  {
    "title": "Rovina Středo-amurská",
    "chapter_number": "",
    "page_number": "121",
    "children": []
  },
  {
    "title": "Přes Malý Chingan",
    "chapter_number": "",
    "page_number": "124",
    "children": []
  },
  {
    "title": "Do Zabajkalska",
    "chapter_number": "",
    "page_number": "128",
    "children": []
  },
  {
    "title": "Sibiří domů",
    "chapter_number": "",
    "page_number": "137",
    "children": []
  }
]
