
[
  {
    "title": "Organisace výstavy",
    "chapter_number": "",
    "page_number": "5-14",
    "children": []
  },
  {
    "title": "Podpory hospodářsko-průmyslové a umělecké výstavě v Hořicích",
    "chapter_number": "",
    "page_number": "15",
    "children": []
  },
  {
    "title": "Sjezdy a slavnosti po dobu výstavní",
    "chapter_number": "",
    "page_number": "16",
    "children": []
  },
  {
    "title": "Slavnost odhalení pomníku Smetanova",
    "chapter_number": "",
    "page_number": "17",
    "children": []
  },
  {
    "title": "Hudební večírky. Skladby hudební. Kapela výstavní",
    "chapter_number": "",
    "page_number": "18",
    "children": []
  },
  {
    "title": "Tamburaši. Závody jednot divadelních ochotníků. Sport",
    "chapter_number": "",
    "page_number": "19",
    "children": []
  },
  {
    "title": "Slavnost husitská",
    "chapter_number": "",
    "page_number": "20",
    "children": []
  },
  {
    "title": "Slavnost národopisná",
    "chapter_number": "",
    "page_number": "21",
    "children": []
  },
  {
    "title": "Vrázův „Svět v obrazích\", loutkové divadlo, panorama kruhové, diorama",
    "chapter_number": "",
    "page_number": "21",
    "children": []
  },
  {
    "title": "Hořice a jejich okolí",
    "chapter_number": "",
    "page_number": "22",
    "children": []
  },
  {
    "title": "Hořice za války pruské",
    "chapter_number": "",
    "page_number": "29",
    "children": []
  },
  {
    "title": "Výstavy v Hořicích",
    "chapter_number": "",
    "page_number": "35",
    "children": []
  },
  {
    "title": "Průvodce výstavou",
    "chapter_number": "",
    "page_number": "38",
    "children": []
  },
  {
    "title": "Smetanova slavnostní síň",
    "chapter_number": "",
    "page_number": "47",
    "children": []
  },
  {
    "title": "Řád pro sbor soudců",
    "chapter_number": "",
    "page_number": "50",
    "children": []
  },
  {
    "title": "Seznam vystavovatelů a vystavených předmětů s přiléhajícími odbornými články",
    "chapter_number": "",
    "page_number": "54",
    "children": []
  },
  {
    "title": "Skupina I. Zemědělství",
    "chapter_number": "",
    "page_number": "54",
    "children": [
      {
        "title": "(Hospodářské zvířectvo, plodiny, zahradnictví, lesnictví a honba, hospodář-ské školství, literatura, hosp. technika, meliorace atd. zvláštní katalog.)",
        "chapter_number": "",
        "page_number": "54",
        "children": []
      },
      {
        "title": "Zemědělský průmysl",
        "chapter_number": "",
        "page_number": "54",
        "children": []
      },
      {
        "title": "Hospodářské stroje a nářadí",
        "chapter_number": "",
        "page_number": "56",
        "children": []
      }
    ]
  },
  {
    "title": "Skupina II. Průmysl",
    "chapter_number": "",
    "page_number": "61",
    "children": [
      {
        "title": "Textilnictví v Hořicích",
        "chapter_number": "",
        "page_number": "61",
        "children": []
      },
      {
        "title": "Textilnictví a příbuzná odvětví",
        "chapter_number": "",
        "page_number": "69",
        "children": []
      },
      {
        "title": "Oděvnictví a příbuzná odvětví",
        "chapter_number": "",
        "page_number": "71",
        "children": []
      },
      {
        "title": "Kůže a její úprava. Výrobky kožené, usně, štětiny. Výrobky živ. sem spadající",
        "chapter_number": "",
        "page_number": "73",
        "children": []
      },
      {
        "title": "Truhlářství, soustružnictví a řezbářství českého severovýchodu",
        "chapter_number": "",
        "page_number": "75",
        "children": []
      },
      {
        "title": "Výrobky ze dřeva, kosti a rohu, proutí, korku, slámy, pryže, perčoviny, moř-ské pěny, jantaru a pod.",
        "chapter_number": "",
        "page_number": "80",
        "children": []
      },
      {
        "title": "Sochařství a kamenictví v Hořicích a okolí",
        "chapter_number": "",
        "page_number": "83",
        "children": []
      },
      {
        "title": "Broušení drahokamů, rytí do drahokamů, zasazování drahokamů, zlatnictví i klenotnictví",
        "chapter_number": "",
        "page_number": "91",
        "children": []
      },
      {
        "title": "Průmyslové a umělecko-prům. zpracování kamene, zvláště hořického pískovce",
        "chapter_number": "",
        "page_number": "94",
        "children": []
      },
      {
        "title": "Průmyslové zpracování hlíny",
        "chapter_number": "",
        "page_number": "100",
        "children": []
      },
      {
        "title": "Umělecké zámečnictví",
        "chapter_number": "",
        "page_number": "103",
        "children": []
      },
      {
        "title": "Výrobky kovové",
        "chapter_number": "",
        "page_number": "107",
        "children": []
      },
      {
        "title": "Výrobky zlaté a stříbrné",
        "chapter_number": "",
        "page_number": "110",
        "children": []
      },
      {
        "title": "Stroje, nástroje, přístroje, patenty",
        "chapter_number": "",
        "page_number": "110",
        "children": []
      },
      {
        "title": "Hodiny, vědecké stroje a přístroje",
        "chapter_number": "",
        "page_number": "112",
        "children": []
      },
      {
        "title": "Hudební nástroje všeho druhu",
        "chapter_number": "",
        "page_number": "112",
        "children": []
      },
      {
        "title": "Průmysl chemický",
        "chapter_number": "",
        "page_number": "113",
        "children": []
      },
      {
        "title": "Hornictví a těžba z říše nerostů",
        "chapter_number": "",
        "page_number": "114",
        "children": []
      },
      {
        "title": "Papírnictví, ozdobnictví a živnosti polygrafické",
        "chapter_number": "",
        "page_number": "114",
        "children": []
      },
      {
        "title": "Výroba nábytku",
        "chapter_number": "",
        "page_number": "116",
        "children": []
      },
      {
        "title": "Stavitelství, inženýrství a živnosti stavební",
        "chapter_number": "",
        "page_number": "118",
        "children": []
      },
      {
        "title": "Prostředky dopravní",
        "chapter_number": "",
        "page_number": "118",
        "children": []
      },
      {
        "title": "Sport, tělocvik, hasičství",
        "chapter_number": "",
        "page_number": "119",
        "children": []
      },
      {
        "title": "Různé jiné výrobky všeho druhu",
        "chapter_number": "",
        "page_number": "119",
        "children": []
      },
      {
        "title": "Ženské ruční práce",
        "chapter_number": "",
        "page_number": "121",
        "children": []
      },
      {
        "title": "Technologie",
        "chapter_number": "",
        "page_number": "123",
        "children": []
      },
      {
        "title": "Vzhůru do Krkonoš",
        "chapter_number": "",
        "page_number": "126",
        "children": []
      },
      {
        "title": "Zvláštní pavillony",
        "chapter_number": "",
        "page_number": "",
        "children": []
      },
      {
        "title": "Pavillon J. O. Jana hraběte z Harrachů",
        "chapter_number": "",
        "page_number": "131",
        "children": []
      },
      {
        "title": "Pavillon Královéhradecký",
        "chapter_number": "",
        "page_number": "132",
        "children": []
      },
      {
        "title": "Pavillon Krkonošský",
        "chapter_number": "",
        "page_number": "135",
        "children": []
      },
      {
        "title": "Krajkářství na Zambersku",
        "chapter_number": "",
        "page_number": "144",
        "children": []
      }
    ]
  },
  {
    "title": "Skupina III. Umění. (Zvláštní katalog.)",
    "chapter_number": "",
    "page_number": "147",
    "children": []
  },
  {
    "title": "Skupina IV. Školství a literatura",
    "chapter_number": "",
    "page_number": "155",
    "children": [
      {
        "title": "Školství v obvodu obchodní a průmyslové komory Liberecké",
        "chapter_number": "",
        "page_number": "157",
        "children": []
      },
      {
        "title": "Ústavy pro výchovu ditek před povinností školní",
        "chapter_number": "",
        "page_number": "157",
        "children": []
      },
      {
        "title": "Obecné školy",
        "chapter_number": "",
        "page_number": "158",
        "children": []
      },
      {
        "title": "Měšťanské a pokračovací školy",
        "chapter_number": "",
        "page_number": "159",
        "children": []
      },
      {
        "title": "Střední školy, odborné školy",
        "chapter_number": "",
        "page_number": "161",
        "children": []
      },
      {
        "title": "Ústavy a spolky dobročinné",
        "chapter_number": "",
        "page_number": "161",
        "children": []
      },
      {
        "title": "Jednotliví vystavovatelé",
        "chapter_number": "",
        "page_number": "166",
        "children": []
      }
    ]
  },
  {
    "title": "Skupina V. Národopis a archaeologie, musea",
    "chapter_number": "",
    "page_number": "166",
    "children": [
      {
        "title": "Archaeologické procházky po okolí Hořickém",
        "chapter_number": "",
        "page_number": "167",
        "children": []
      }
    ]
  },
  {
    "title": "Skupina VI. Socialní politika a zdravotnictví",
    "chapter_number": "",
    "page_number": "171",
    "children": []
  },
  {
    "title": "Dodatek vystavovatelů",
    "chapter_number": "",
    "page_number": "172",
    "children": []
  },
  {
    "title": "Český klub fotografů amatérů v Praze",
    "chapter_number": "",
    "page_number": "175",
    "children": []
  },
  {
    "title": "Inserty",
    "chapter_number": "",
    "page_number": "1-188",
    "children": []
  }
]
