
[
  {
    "title": "Von den gewöhnlichen Ursachen des Rauchens der Schornsteine",
    "chapter_number": "",
    "page_number": "7",
    "children": [
      {
        "title": "der nachtheiligen Einwirkung des Windes",
        "chapter_number": "",
        "page_number": "8",
        "children": []
      },
      {
        "title": "dem Einfluße der Atmosphäre",
        "chapter_number": "",
        "page_number": "9",
        "children": []
      },
      {
        "title": "der Einwirkung des Regens",
        "chapter_number": "",
        "page_number": "11",
        "children": []
      },
      {
        "title": "der Einwirkung der Sonne",
        "chapter_number": "",
        "page_number": "12",
        "children": []
      }
    ]
  },
  {
    "title": "Anlage und Bau der Schornsteine",
    "chapter_number": "",
    "page_number": "13",
    "children": []
  },
  {
    "title": "Geschleifte Schornsteine",
    "chapter_number": "",
    "page_number": "15",
    "children": []
  },
  {
    "title": "Höhe der Schornsteine",
    "chapter_number": "",
    "page_number": "18",
    "children": []
  },
  {
    "title": "Anwendung des Manometers",
    "chapter_number": "",
    "page_number": "20",
    "children": []
  },
  {
    "title": "Blechkreuz - Aufsak",
    "chapter_number": "",
    "page_number": "23",
    "children": []
  },
  {
    "title": "Hängende Thürchen von Hrn. Buschendorf",
    "chapter_number": "",
    "page_number": "24",
    "children": []
  },
  {
    "title": "Eisenblecherne Klappe von Hrn. Siegfried",
    "chapter_number": "",
    "page_number": "26",
    "children": []
  },
  {
    "title": "Blechkasten von Hrn. Bernhard",
    "chapter_number": "",
    "page_number": "27",
    "children": []
  },
  {
    "title": "Blechhaube von Hrn. Millet",
    "chapter_number": "",
    "page_number": "28",
    "children": []
  },
  {
    "title": "Windfahnen mit dem Schild von Hrn. Halliday",
    "chapter_number": "",
    "page_number": "29",
    "children": []
  },
  {
    "title": "Eine einfache Konstruktion des Essenkopfes",
    "chapter_number": "",
    "page_number": "30",
    "children": [
      {
        "title": "andere Konstruktion des Essenkopfes von dem Verfasser",
        "chapter_number": "",
        "page_number": "32",
        "children": []
      },
      {
        "title": "Konstruktion des Essenkopfes von Hrn. Anaker",
        "chapter_number": "",
        "page_number": "33",
        "children": []
      }
    ]
  },
  {
    "title": "Konstruktion des Essenkopfes von Hrn. Schulze",
    "chapter_number": "",
    "page_number": "",
    "children": []
  },
   {
    "title": "Die einfache Maschine von dem Verfasser",
    "chapter_number": "",
    "page_number": "37",
    "children": [
      {
        "title": "doppelte",
        "chapter_number": "",
        "page_number": "41",
        "children": []
      }
    ]
  },
  {
    "title": "Beilagen",
    "chapter_number": "",
    "page_number": "45",
    "children": []
  },
  {
    "title": "Erklärung der Zeichenblätter",
    "chapter_number": "",
    "page_number": "47",
    "children": []
  }
]
