
[
  {
    "title": "Drittes Lebensalter",
    "chapter_number": "",
    "page_number": "79",
    "children": []
  },
  {
    "title": "Viertes Lebensalter",
    "chapter_number": "",
    "page_number": "80",
    "children": []
  },
  {
    "title": "Fünftes Lebensalter",
    "chapter_number": "",
    "page_number": "82",
    "children": []
  },
  {
    "title": "Physische Einflüsse auf die Raupen hinsichtlich des Lichtes, der Wärme, der Luft und der Feuchtigkeit",
    "chapter_number": "",
    "page_number": "86",
    "children": []
  },
  {
    "title": "Das Futter und die Fütterung",
    "chapter_number": "",
    "page_number": "90",
    "children": []
  },
  {
    "title": "Die Reinigung der Lager oder Hürden",
    "chapter_number": "",
    "page_number": "95",
    "children": []
  },
  {
    "title": "Krankheiten der Seidenraupen",
    "chapter_number": "",
    "page_number": "97",
    "children": [
      {
        "title": "Schwindsucht",
        "chapter_number": "",
        "page_number": "97",
        "children": []
      },
      {
        "title": "Faul - oder Schlaffsucht",
        "chapter_number": "",
        "page_number": "98",
        "children": []
      },
      {
        "title": "Fettsucht",
        "chapter_number": "",
        "page_number": "98",
        "children": []
      },
      {
        "title": "Gelbsucht",
        "chapter_number": "",
        "page_number": "99",
        "children": []
      },
      {
        "title": "Durchsichtigkeit oder Wassersucht",
        "chapter_number": "",
        "page_number": "99",
        "children": []
      },
      {
        "title": "Staarsucht oder Flecksucht auch Verkalkung",
        "chapter_number": "",
        "page_number": "100",
        "children": []
      },
      {
        "title": "Kurzspinnen",
        "chapter_number": "",
        "page_number": "101",
        "children": []
      }
    ]
  },
  {
    "title": "Feinde der Seidenraupen",
    "chapter_number": "",
    "page_number": "102",
    "children": []
  },
  {
    "title": "Das Einspinnen der Seidenraupe",
    "chapter_number": "",
    "page_number": "103",
    "children": []
  },
  {
    "title": "Ernte oder Abnahme der Cocons",
    "chapter_number": "",
    "page_number": "103",
    "children": []
  },
  {
    "title": "Sortiren der Cocons",
    "chapter_number": "",
    "page_number": "108",
    "children": []
  },
  {
    "title": "Weitere Behandlung, Aufbewahrung und Versendung der Cocons",
    "chapter_number": "",
    "page_number": "110",
    "children": []
  },
  {
    "title": "Gewinnung der Raupeneier (Grain's)",
    "chapter_number": "",
    "page_number": "112",
    "children": []
  },
  {
    "title": "Das Abhaspeln der Cocons oder Fadenbildung der Seide",
    "chapter_number": "",
    "page_number": "115",
    "children": []
  },
  {
    "title": "Die Verarbeitung der Abfälle zu Floretseide",
    "chapter_number": "",
    "page_number": "127",
    "children": []
  }
]
