
[
  {
    "title": "Pohádka z vyšini",
    "chapter_number": "1",
    "page_number": "5",
    "children": []
  },
  {
    "title": "Veverčin dar",
    "chapter_number": "2",
    "page_number": "17",
    "children": []
  },
  {
    "title": "Lípové lýčí",
    "chapter_number": "3",
    "page_number": "29",
    "children": []
  },
  {
    "title": "Dřevorubci",
    "chapter_number": "4",
    "page_number": "39",
    "children": []
  },
  {
    "title": "Kolomazník",
    "chapter_number": "5",
    "page_number": "53",
    "children": []
  },
  {
    "title": "V pískovnici",
    "chapter_number": "6",
    "page_number": "67",
    "children": []
  },
  {
    "title": "Hadí kůže",
    "chapter_number": "7",
    "page_number": "79",
    "children": []
  },
  {
    "title": "Dřevěná pohádka",
    "chapter_number": "8",
    "page_number": "91",
    "children": []
  },
  {
    "title": "Na Žehrově",
    "chapter_number": "9",
    "page_number": "101",
    "children": []
  }
]
