
[
  {
    "title": "Evangelíkův poklad",
    "chapter_number": "",
    "page_number": "3",
    "children": []
  },
  {
    "title": "Pověsti o Boru",
    "chapter_number": "",
    "page_number": "27",
    "children": []
  },
  {
    "title": "Zrádce",
    "chapter_number": "",
    "page_number": "51",
    "children": []
  },
  {
    "title": "Pověsti o hradu Skalách",
    "chapter_number": "",
    "page_number": "91",
    "children": []
  },
  {
    "title": "Povstání selské na Policku",
    "chapter_number": "",
    "page_number": "112",
    "children": []
  },
  {
    "title": "Úpičtí rytíři",
    "chapter_number": "",
    "page_number": "135",
    "children": []
  },
  {
    "title": "O strašidelném bubeníkovi",
    "chapter_number": "",
    "page_number": "139",
    "children": []
  },
  {
    "title": "Založení Boušínského kostelíčka",
    "chapter_number": "",
    "page_number": "145",
    "children": []
  },
  {
    "title": "O Vlčinci",
    "chapter_number": "",
    "page_number": "151",
    "children": []
  },
  {
    "title": "Pánova cesta",
    "chapter_number": "",
    "page_number": "159",
    "children": []
  },
  {
    "title": "Klášterní pověsti Polické",
    "chapter_number": "",
    "page_number": "191",
    "children": []
  },
  {
    "title": "O Čermenském rychláři",
    "chapter_number": "",
    "page_number": "221",
    "children": []
  },
  {
    "title": "Kolda ze Žampachu na Náchodě",
    "chapter_number": "",
    "page_number": "231",
    "children": []
  },
  {
    "title": "Kovářova rokle",
    "chapter_number": "",
    "page_number": "241",
    "children": []
  },
  {
    "title": "Vodníkova nevěsta",
    "chapter_number": "",
    "page_number": "281",
    "children": []
  },
  {
    "title": "Jaroměřský hejtman",
    "chapter_number": "",
    "page_number": "295",
    "children": []
  },
  {
    "title": "Židovka",
    "chapter_number": "",
    "page_number": "305",
    "children": []
  },
  {
    "title": "Čertovinská šibenice",
    "chapter_number": "",
    "page_number": "309",
    "children": []
  },
  {
    "title": "Loupežníkova sekyra",
    "chapter_number": "",
    "page_number": "317",
    "children": []
  },
  {
    "title": "Podkova krále Bedřicha",
    "chapter_number": "",
    "page_number": "329",
    "children": []
  },
  {
    "title": "Zkamenělý les Radvanický",
    "chapter_number": "",
    "page_number": "335",
    "children": []
  },
  {
    "title": "Poklad na „Švédském vrchu“",
    "chapter_number": "",
    "page_number": "339",
    "children": []
  },
  {
    "title": "Bouřlivý sněm na Dobeníně",
    "chapter_number": "",
    "page_number": "345",
    "children": []
  },
  {
    "title": "Poslední útulek J. A. Komenského",
    "chapter_number": "",
    "page_number": "349",
    "children": []
  },
  {
    "title": "O Turovu",
    "chapter_number": "",
    "page_number": "367",
    "children": []
  },
  {
    "title": "Pán z Homole",
    "chapter_number": "",
    "page_number": "377",
    "children": []
  }
]
