
[
  {
    "title": "Předmluva",
    "chapter_number": "",
    "page_number": "5",
    "children": []
  },
  {
    "title": "Úvod",
    "chapter_number": "",
    "page_number": "8",
    "children": []
  },
  {
    "title": "Rok 1914",
    "chapter_number": "",
    "page_number": "12",
    "children": []
  },
  {
    "title": "Rok 1915",
    "chapter_number": "",
    "page_number": "31",
    "children": []
  },
  {
    "title": "Rok 1916",
    "chapter_number": "",
    "page_number": "92",
    "children": []
  },
  {
    "title": "Rok 1917",
    "chapter_number": "",
    "page_number": "131",
    "children": []
  },
  {
    "title": "Rok 1918",
    "chapter_number": "",
    "page_number": "163",
    "children": []
  },
  {
    "title": "Převrat",
    "chapter_number": "",
    "page_number": "199",
    "children": []
  },
  {
    "title": "Doplňky",
    "chapter_number": "",
    "page_number": "281",
    "children": []
  },
  {
    "title": "Kabíček Jan: Kapitán Antonín Halbich",
    "chapter_number": "",
    "page_number": "284",
    "children": []
  },
  {
    "title": "Přílohy: I. Vyhlášky",
    "chapter_number": "",
    "page_number": "288",
    "children": []
  },
  {
    "title": "II. Z dopisů jaroměřských vojínů",
    "chapter_number": "",
    "page_number": "297",
    "children": []
  },
  {
    "title": "III. Samospráva a státní úřady za války",
    "chapter_number": "",
    "page_number": "306",
    "children": []
  },
  {
    "title": "IV. Jaroměřští legionáři",
    "chapter_number": "",
    "page_number": "309",
    "children": []
  },
  {
    "title": "V. Seznam vojínů",
    "chapter_number": "",
    "page_number": "311",
    "children": []
  }
]
