
[
  {
    "title": "Dějinné tradice polského národohospodářství",
    "chapter_number": "",
    "page_number": "241",
    "children": []
  },
  {
    "title": "K úkolům polského národohospodářství po válce",
    "chapter_number": "",
    "page_number": "247",
    "children": []
  },
  {
    "title": "O znárodnění průmyslu",
    "chapter_number": "",
    "page_number": "268",
    "children": []
  },
  {
    "title": "Emigrace, parcelace a rolnické reformy",
    "chapter_number": "",
    "page_number": "273",
    "children": []
  },
  {
    "title": "Vyhlídky haličského exportu",
    "chapter_number": "",
    "page_number": "334",
    "children": []
  },
  {
    "title": "Z hospodářských snah velkopolska",
    "chapter_number": "",
    "page_number": "348",
    "children": []
  },
  {
    "title": "Několik poznámek retrospektivně-historických",
    "chapter_number": "",
    "page_number": "387",
    "children": []
  },
  {
    "title": "Vyhlídky a nebezpečí velkoprůmyslu",
    "chapter_number": "",
    "page_number": "431",
    "children": []
  },
  {
    "title": "Reorganisace společenského útvaru",
    "chapter_number": "",
    "page_number": "434",
    "children": []
  },
  {
    "title": "Hospodářský stav Polska od jeho osamostatnění do polovice roku 1922",
    "chapter_number": "",
    "page_number": "439",
    "children": []
  },
  {
    "title": "Literatura",
    "chapter_number": "",
    "page_number": "446",
    "children": []
  },
  {
    "title": "Část všeobecně kulturní",
    "chapter_number": "III",
    "page_number": "449",
    "children": []
  },
  {
    "title": "Celkový charakter polské civilisace",
    "chapter_number": "",
    "page_number": "451",
    "children": []
  },
  {
    "title": "Rozvoj a dnešní stav polského školství",
    "chapter_number": "",
    "page_number": "455",
    "children": []
  },
  {
    "title": "Osvěta mimoškolská",
    "chapter_number": "",
    "page_number": "463",
    "children": []
  },
  {
    "title": "Malířství",
    "chapter_number": "",
    "page_number": "478",
    "children": []
  },
  {
    "title": "K rozvoji polské hudby",
    "chapter_number": "",
    "page_number": "489",
    "children": []
  },
  {
    "title": "Dnešní stav polského tisku",
    "chapter_number": "",
    "page_number": "495",
    "children": []
  },
  {
    "title": "Z vlivů polského písemnictví na Slovanstvo",
    "chapter_number": "",
    "page_number": "504",
    "children": []
  },
  {
    "title": "Hlavní směry v polském písemnictví",
    "chapter_number": "",
    "page_number": "507",
    "children": []
  },
  {
    "title": "Několik kapitol z dějin novodobého polského románu",
    "chapter_number": "",
    "page_number": "514",
    "children": []
  },
  {
    "title": "Stručný přehled básnictví",
    "chapter_number": "",
    "page_number": "624",
    "children": []
  },
  {
    "title": "K vývoji dramatu",
    "chapter_number": "",
    "page_number": "692",
    "children": []
  }
]
