
[
  {
    "title": "Předmluva",
    "chapter_number": "",
    "page_number": "7",
    "children": []
  },
  {
    "title": "Úvod (8 statí)",
    "chapter_number": "",
    "page_number": "13",
    "children": []
  },
  {
    "title": "Rostlinopis (67 statí, 77 vyobrazení)",
    "chapter_number": "",
    "page_number": "17",
    "children": []
  },
  {
    "title": "Živočichopis (194 statě, 149 vyobrazení)",
    "chapter_number": "",
    "page_number": "121",
    "children": []
  },
  {
    "title": "Nerosłopis (78 statí, 4 vyobrazení)",
    "chapter_number": "",
    "page_number": "307",
    "children": []
  },
  {
    "title": "Počtářství (34 statě)",
    "chapter_number": "",
    "page_number": "337",
    "children": []
  },
  {
    "title": "Měřictví (42 statě, 25 vyobrazení)",
    "chapter_number": "",
    "page_number": "356",
    "children": []
  },
  {
    "title": "Zeměměřictví (100 statí, 68 vyobrazení)",
    "chapter_number": "",
    "page_number": "378",
    "children": []
  },
  {
    "title": "Pěstba lesa (226 statí, 12 vyobrazení)",
    "chapter_number": "",
    "page_number": "410",
    "children": []
  },
  {
    "title": "Ochrana lesa (109 statí, 33 vyobrazení)",
    "chapter_number": "",
    "page_number": "466",
    "children": []
  },
  {
    "title": "Těžba lesa (101 staf, 27 vyobrazení)",
    "chapter_number": "",
    "page_number": "526",
    "children": []
  },
  {
    "title": "Dodatek",
    "chapter_number": "",
    "page_number": "562",
    "children": []
  },
  {
    "title": "Doslov.",
    "chapter_number": "",
    "page_number": "572",
    "children": []
  },
  {
    "title": "Opravy",
    "chapter_number": "",
    "page_number": "574",
    "children": []
  }
]
