
[
  {
    "title": "POZNÁMKY",
    "chapter_number": "",
    "page_number": "299",
    "children": [
      {
        "title": "Na okraj Erbenových básní",
        "chapter_number": "",
        "page_number": "355",
        "children": []
      }
    ]
  },
  {
    "title": "OBRAZOVÉ PŘÍLOHY",
    "chapter_number": "",
    "page_number": "",
    "children": [
      {
        "title": "KAREL JAROMÍR ERBEN. Olejomalba",
        "chapter_number": "",
        "page_number": "",
        "children": [
          {
            "title": "F. Gérarda 1845-",
            "chapter_number": "",
            "page_number": "64",
            "children": []
          }
        ]
      },
      {
        "title": "NÁČRTKY VODNÍKA. Erbenův rukopis z ma- kuláře Kytice",
        "chapter_number": "",
        "page_number": "160",
        "children": []
      }
    ]
  }
]
