
[
  {
    "title": "O vodě, příbytku zvířat a rostlin",
    "chapter_number": "1",
    "page_number": "1",
    "children": []
  },
  {
    "title": "Koloběh vodní",
    "chapter_number": "2",
    "page_number": "5",
    "children": []
  },
  {
    "title": "Druhy vodstva",
    "chapter_number": "3",
    "page_number": "7",
    "children": []
  },
  {
    "title": "Vlastnosti vod",
    "chapter_number": "4",
    "page_number": "37",
    "children": []
  },
  {
    "title": "Pohyby vodstva",
    "chapter_number": "5",
    "page_number": "60",
    "children": []
  },
  {
    "title": "Výzkum vodstva",
    "chapter_number": "6",
    "page_number": "85",
    "children": []
  },
  {
    "title": "Vzájemné vztahy a životní podmínky vodních rostlin i zvířat",
    "chapter_number": "7",
    "page_number": "94",
    "children": []
  },
  {
    "title": "Život v destillované vodě",
    "chapter_number": "8",
    "page_number": "102",
    "children": []
  },
  {
    "title": "Pohledy do vod znečištěných",
    "chapter_number": "9",
    "page_number": "133",
    "children": []
  },
  {
    "title": "Drobný svět v mechu",
    "chapter_number": "10",
    "page_number": "162",
    "children": []
  },
  {
    "title": "V klínu jezerním",
    "chapter_number": "11",
    "page_number": "186",
    "children": []
  },
  {
    "title": "Černé a Čertovo jezero na Šumavě",
    "chapter_number": "12",
    "page_number": "207",
    "children": []
  },
  {
    "title": "Památné zvířeny Bajkalského a Tanganického jezera",
    "chapter_number": "13",
    "page_number": "213",
    "children": []
  },
  {
    "title": "Co oživuje kaluže dešťové a sněhové",
    "chapter_number": "14",
    "page_number": "216",
    "children": []
  },
  {
    "title": "O pestrém životě v našich tůních",
    "chapter_number": "15",
    "page_number": "219",
    "children": []
  },
  {
    "title": "Z vědomostí rybnikářských",
    "chapter_number": "16",
    "page_number": "270",
    "children": []
  },
  {
    "title": "O zvířeně a květeně tekoucích vod",
    "chapter_number": "17",
    "page_number": "281",
    "children": []
  },
  {
    "title": "O životě v podzemních vodách",
    "chapter_number": "18",
    "page_number": "301",
    "children": []
  },
  {
    "title": "Z výletů k Severnímu moři",
    "chapter_number": "19",
    "page_number": "307",
    "children": []
  },
  {
    "title": "Na pobřeží baltickém",
    "chapter_number": "20",
    "page_number": "417",
    "children": []
  },
  {
    "title": "Z potulek po moři Jaderském",
    "chapter_number": "21",
    "page_number": "427",
    "children": []
  },
  {
    "title": "Ze života na korálových útesech",
    "chapter_number": "22",
    "page_number": "479",
    "children": []
  },
  {
    "title": "V polárních vodách",
    "chapter_number": "23",
    "page_number": "489",
    "children": []
  }
]
